financial_reporter/__init__.py
financial_reporter/__main__.py
financial_reporter/calculations.py
financial_reporter_vtcu-0.1.1.dist-info/METADATA
financial_reporter_vtcu-0.1.1.dist-info/WHEEL
financial_reporter_vtcu-0.1.1.dist-info/top_level.txt
financial_reporter_vtcu-0.1.1.dist-info/RECORD
