Metadata-Version: 2.1
Name: financial-reporter-vtcu
Version: 0.1.1
Summary: Пакет для загрузки, группировки транзакций и генерации финансовых отчётов.
Author: vtcu
Author-email: vtcu <sleeve_thinker_0d@icloud.com>
License: MIT
Classifier: Programming Language :: Python :: 3
Classifier: License :: OSI Approved :: MIT License
Classifier: Operating System :: OS Independent
Requires-Python: >=3.8
Requires-Dist: pandas>=1.0.0
Provides-Extra: dev
Requires-Dist: pytest>=6.0.0; extra == "dev"
Requires-Dist: flake8>=3.8.0; extra == "dev"
